hush/__init__.py
hush/cli.py
hush/main.py
hush/web_gateway.py
hush/crypto/__init__.py
hush/crypto/crypto.py
hush/net/__init__.py
hush/net/discovery.py
hush/net/peer.py
hush/net/server.py
hush/tui/__init__.py
hush/tui/interface.py
hush/utils/__init__.py
hush/utils/settings.py
hush_p2p-2.0.5.dist-info/METADATA
hush_p2p-2.0.5.dist-info/WHEEL
hush_p2p-2.0.5.dist-info/entry_points.txt
hush_p2p-2.0.5.dist-info/top_level.txt
hush_p2p-2.0.5.dist-info/RECORD
